SLiM_phys/Dispersion_func.py
SLiM_phys/SLiM_obj.py
SLiM_phys/__init__.py
SLiM_phys/file_IO_obj.py
SLiM_phys/SLiM_NN/Dispersion_NN.py
SLiM_phys/SLiM_NN/__init__.py
SLiM_phys/SLiM_NN/data_tool.py
SLiM_phys/SLiM_NN/git_download.py
SLiM_phys/Tools/DispersionRelationDeterminantFullConductivityZeff.py
SLiM_phys/Tools/Gaussian_fit.py
SLiM_phys/Tools/ParIO.py
SLiM_phys/Tools/V2_DispersionRelationDeterminantFullConductivityZeff.py
SLiM_phys/Tools/__init__.py
SLiM_phys/Tools/efittools.py
SLiM_phys/Tools/finite_differences.py
SLiM_phys/Tools/finite_differences_x.py
SLiM_phys/Tools/interp.py
SLiM_phys/Tools/max_parity_calculator.py
SLiM_phys/Tools/max_pedestal_finder.py
SLiM_phys/Tools/max_stat_tool.py
SLiM_phys/Tools/parIOWrapper.py
SLiM_phys/Tools/read_EFIT.py
SLiM_phys/Tools/read_EFIT_file.py
SLiM_phys/Tools/read_gfile.py
SLiM_phys/Tools/read_iterdb.py
SLiM_phys/Tools/read_iterdb_file.py
SLiM_phys/Tools/read_pfile.py
SLiM_phys/Tools/read_profiles.py
SLiM_phys/Tools/read_write_geometry.py
SLiM_phys/Tools/write_gfile.py
SLiM_phys/Tools/write_iterdb.py
SLiM_phys/Tools/write_pfile.py
SLiM_phys-1.0.2.dist-info/LICENSE
SLiM_phys-1.0.2.dist-info/METADATA
SLiM_phys-1.0.2.dist-info/WHEEL
SLiM_phys-1.0.2.dist-info/top_level.txt
SLiM_phys-1.0.2.dist-info/RECORD
