Metadata-Version: 2.1
Name: SLiM-phys
Version: 1.0.2
Summary: SLiM project and its supporting scripts
Author: maxtcurie (Max Curie)
Author-email: <maxtcurie@gmail.com>
License: UNKNOWN
Keywords: python,plasma,physics,microtearing modes,reduced model,neural network
Platform: UNKNOWN
Classifier: Development Status :: 3 - Alpha
Classifier: Intended Audience :: Education
Classifier: Programming Language :: Python :: 3
Classifier: Operating System :: Unix
Classifier: Operating System :: MacOS :: MacOS X
Classifier: Operating System :: Microsoft :: Windows
License-File: LICENSE
